{
	"format_version": "1.17.0",
	"minecraft:block": {
		"description": {
			"identifier": "sp:alchemic_circle"
		},
		"components": {
			"minecraft:material_instances": {
				"*": {
					"texture": "alc",
					"render_method": "alpha_test",
					"ambient_occlusion": false
				}
			},
			"minecraft:crafting_table": {
				"crafting_tags": [
					"caldron"
				],
				"custom_description": "ยง1Cerchio Alchemico",
				"grid_size": 3
			},
			"minecraft:geometry": "geometry.alc",
			"minecraft:entity_collision": {
				"origin": [
					-8,
					0.2,
					-8
				],
				"size": [
					16,
					1,
					16
				]
			},
			"minecraft:pick_collision": {
				"origin": [
					-8,
					0.2,
					-8
				],
				"size": [
					16,
					1,
					16
				]
			},
			"minecraft:block_light_emission": 0.3,
			"minecraft:block_light_absorption": 0.3
		},
		"events": {}
	}
}